LICENSE.txt
MANIFEST.in
README.md
pysymlog.py
setup.py
pysymlog.egg-info/PKG-INFO
pysymlog.egg-info/SOURCES.txt
pysymlog.egg-info/dependency_links.txt
pysymlog.egg-info/requires.txt
pysymlog.egg-info/top_level.txt