Metadata-Version: 2.1
Name: pysymlog
Version: 1.0.1
Summary: Symmetric (signed) logarithmic scale
Home-page: https://github.com/pjcigan/pysymlog
Author: Phil Cigan
Author-email: 
License: MIT
License-File: LICENSE.txt
Requires-Dist: numpy
Provides-Extra: matplotlib
Requires-Dist: matplotlib; extra == "matplotlib"
Provides-Extra: plotly
Requires-Dist: plotly; extra == "plotly"
